{
  "minecraft:recipes/tools/fishing_rod": {
    "criteria": {
      "has_string": "2021-05-28 17:53:02 -0400"
    },
    "done": true
  },
  "minecraft:recipes/combat/bow": {
    "criteria": {
      "has_string": "2021-05-28 17:53:02 -0400"
    },
    "done": true
  },
  "minecraft:recipes/building_blocks/polished_andesite_slab": {
    "criteria": {
      "has_polished_andesite": "2021-05-28 18:39:53 -0400"
    },
    "done": true
  },
  "minecraft:recipes/building_blocks/quartz_pillar": {
    "criteria": {
      "has_quartz_pillar": "2021-05-28 17:53:02 -0400"
    },
    "done": true
  },
  "minecraft:recipes/tools/wooden_axe": {
    "criteria": {
      "has_stick": "2021-05-28 19:02:13 -0400"
    },
    "done": true
  },
  "minecraft:recipes/redstone/lever": {
    "criteria": {
      "has_cobblestone": "2021-05-28 17:53:02 -0400"
    },
    "done": true
  },
  "minecraft:recipes/building_blocks/cobblestone_stairs_from_cobblestone_stonecutting": {
    "criteria": {
      "has_cobblestone": "2021-05-28 17:53:02 -0400"
    },
    "done": true
  },
  "minecraft:recipes/decorations/cyan_glazed_terracotta": {
    "criteria": {
      "has_cyan_terracotta": "2021-05-28 18:46:44 -0400"
    },
    "done": true
  },
  "minecraft:recipes/building_blocks/stone_stairs_from_stone_stonecutting": {
    "criteria": {
      "has_stone": "2021-05-28 18:47:10 -0400"
    },
    "done": true
  },
  "minecraft:recipes/building_blocks/smooth_stone_slab": {
    "criteria": {
      "has_smooth_stone": "2021-05-28 17:53:02 -0400"
    },
    "done": true
  },
  "minecraft:recipes/decorations/gray_glazed_terracotta": {
    "criteria": {
      "has_gray_terracotta": "2021-05-28 18:03:03 -0400"
    },
    "done": true
  },
  "minecraft:recipes/building_blocks/stone_bricks": {
    "criteria": {
      "has_stone": "2021-05-28 18:47:10 -0400"
    },
    "done": true
  },
  "minecraft:recipes/building_blocks/stone_bricks_from_stone_stonecutting": {
    "criteria": {
      "has_stone": "2021-05-28 18:47:10 -0400"
    },
    "done": true
  },
  "minecraft:recipes/decorations/loom": {
    "criteria": {
      "has_string": "2021-05-28 17:53:02 -0400"
    },
    "done": true
  },
  "minecraft:recipes/building_blocks/polished_andesite_stairs": {
    "criteria": {
      "has_polished_andesite": "2021-05-28 18:39:53 -0400"
    },
    "done": true
  },
  "minecraft:recipes/building_blocks/cracked_polished_blackstone_bricks": {
    "criteria": {
      "has_blackstone_bricks": "2021-05-28 18:03:21 -0400"
    },
    "done": true
  },
  "minecraft:story/mine_stone": {
    "criteria": {
      "get_stone": "2021-05-28 17:53:02 -0400"
    },
    "done": true
  },
  "minecraft:recipes/building_blocks/stone": {
    "criteria": {
      "has_cobblestone": "2021-05-28 17:53:02 -0400"
    },
    "done": true
  },
  "minecraft:recipes/decorations/furnace": {
    "criteria": {
      "has_cobblestone": "2021-05-28 17:53:02 -0400"
    },
    "done": true
  },
  "minecraft:recipes/decorations/stonecutter": {
    "criteria": {
      "has_stone": "2021-05-28 18:47:10 -0400"
    },
    "done": true
  },
  "minecraft:recipes/building_blocks/polished_blackstone_brick_slab": {
    "criteria": {
      "has_polished_blackstone_bricks": "2021-05-28 18:03:21 -0400"
    },
    "done": true
  },
  "minecraft:adventure/adventuring_time": {
    "criteria": {
      "minecraft:plains": "2021-05-28 17:53:02 -0400"
    },
    "done": false
  },
  "minecraft:recipes/decorations/armor_stand": {
    "criteria": {
      "has_stone_slab": "2021-05-28 18:45:49 -0400"
    },
    "done": true
  },
  "minecraft:recipes/decorations/campfire": {
    "criteria": {
      "has_stick": "2021-05-28 19:02:13 -0400"
    },
    "done": true
  },
  "minecraft:recipes/misc/charcoal": {
    "criteria": {
      "has_log": "2021-05-28 18:18:16 -0400"
    },
    "done": true
  },
  "minecraft:recipes/tools/wooden_pickaxe": {
    "criteria": {
      "has_stick": "2021-05-28 19:02:13 -0400"
    },
    "done": true
  },
  "minecraft:recipes/building_blocks/cobblestone_slab_from_cobblestone_stonecutting": {
    "criteria": {
      "has_cobblestone": "2021-05-28 17:53:02 -0400"
    },
    "done": true
  },
  "minecraft:recipes/building_blocks/smooth_stone": {
    "criteria": {
      "has_stone": "2021-05-28 18:47:10 -0400"
    },
    "done": true
  },
  "minecraft:recipes/decorations/blast_furnace": {
    "criteria": {
      "has_smooth_stone": "2021-05-28 17:53:02 -0400"
    },
    "done": true
  },
  "minecraft:recipes/decorations/ladder": {
    "criteria": {
      "has_stick": "2021-05-28 19:02:13 -0400"
    },
    "done": true
  },
  "minecraft:recipes/decorations/chest": {
    "criteria": {
      "has_lots_of_items": "2021-05-28 17:53:02 -0400"
    },
    "done": true
  },
  "minecraft:recipes/building_blocks/stone_slab_from_stone_stonecutting": {
    "criteria": {
      "has_stone": "2021-05-28 18:47:10 -0400"
    },
    "done": true
  },
  "minecraft:recipes/combat/stone_sword": {
    "criteria": {
      "has_cobblestone": "2021-05-28 17:53:02 -0400"
    },
    "done": true
  },
  "minecraft:recipes/building_blocks/chiseled_stone_bricks_stone_from_stonecutting": {
    "criteria": {
      "has_stone": "2021-05-28 18:47:10 -0400"
    },
    "done": true
  },
  "minecraft:recipes/building_blocks/quartz_stairs": {
    "criteria": {
      "has_quartz_pillar": "2021-05-28 17:53:02 -0400"
    },
    "done": true
  },
  "minecraft:recipes/building_blocks/quartz_slab": {
    "criteria": {
      "has_quartz_pillar": "2021-05-28 17:53:02 -0400"
    },
    "done": true
  },
  "minecraft:recipes/decorations/painting": {
    "criteria": {
      "has_wool": "2021-05-28 18:13:57 -0400"
    },
    "done": true
  },
  "minecraft:recipes/decorations/cobblestone_wall": {
    "criteria": {
      "has_cobblestone": "2021-05-28 17:53:02 -0400"
    },
    "done": true
  },
  "minecraft:recipes/tools/wooden_shovel": {
    "criteria": {
      "has_stick": "2021-05-28 19:02:13 -0400"
    },
    "done": true
  },
  "minecraft:recipes/tools/stone_pickaxe": {
    "criteria": {
      "has_cobblestone": "2021-05-28 17:53:02 -0400"
    },
    "done": true
  },
  "minecraft:recipes/misc/white_dye": {
    "criteria": {
      "has_bone_meal": "2021-05-28 18:17:45 -0400"
    },
    "done": true
  },
  "minecraft:recipes/building_blocks/stone_slab": {
    "criteria": {
      "has_stone": "2021-05-28 18:47:10 -0400"
    },
    "done": true
  },
  "minecraft:recipes/decorations/black_carpet": {
    "criteria": {
      "has_black_wool": "2021-05-28 18:13:57 -0400"
    },
    "done": true
  },
  "minecraft:recipes/redstone/stone_pressure_plate": {
    "criteria": {
      "has_stone": "2021-05-28 18:47:10 -0400"
    },
    "done": true
  },
  "minecraft:recipes/decorations/polished_blackstone_brick_wall": {
    "criteria": {
      "has_polished_blackstone_bricks": "2021-05-28 18:03:21 -0400"
    },
    "done": true
  },
  "minecraft:recipes/building_blocks/stone_brick_slab_from_stone_stonecutting": {
    "criteria": {
      "has_stone": "2021-05-28 18:47:10 -0400"
    },
    "done": true
  },
  "minecraft:recipes/decorations/black_bed": {
    "criteria": {
      "has_black_wool": "2021-05-28 18:13:57 -0400"
    },
    "done": true
  },
  "minecraft:recipes/decorations/cobblestone_wall_from_cobblestone_stonecutting": {
    "criteria": {
      "has_cobblestone": "2021-05-28 17:53:02 -0400"
    },
    "done": true
  },
  "minecraft:recipes/building_blocks/polished_blackstone_brick_slab_from_polished_blackstone_bricks_stonecutting": {
    "criteria": {
      "has_polished_blackstone_bricks": "2021-05-28 18:03:21 -0400"
    },
    "done": true
  },
  "minecraft:recipes/building_blocks/cut_sandstone_slab": {
    "criteria": {
      "has_cut_sandstone": "2021-05-28 17:53:02 -0400"
    },
    "done": true
  },
  "minecraft:recipes/building_blocks/polished_andesite_slab_from_polished_andesite_stonecutting": {
    "criteria": {
      "has_polished_andesite": "2021-05-28 18:39:53 -0400"
    },
    "done": true
  },
  "minecraft:recipes/decorations/stone_brick_walls_from_stone_stonecutting": {
    "criteria": {
      "has_stone": "2021-05-28 18:47:10 -0400"
    },
    "done": true
  },
  "minecraft:recipes/combat/wooden_sword": {
    "criteria": {
      "has_stick": "2021-05-28 19:02:13 -0400"
    },
    "done": true
  },
  "minecraft:recipes/tools/stone_shovel": {
    "criteria": {
      "has_cobblestone": "2021-05-28 17:53:02 -0400"
    },
    "done": true
  },
  "minecraft:recipes/building_blocks/stone_brick_stairs_from_stone_stonecutting": {
    "criteria": {
      "has_stone": "2021-05-28 18:47:10 -0400"
    },
    "done": true
  },
  "minecraft:recipes/building_blocks/oak_planks": {
    "criteria": {
      "has_logs": "2021-05-28 18:18:16 -0400"
    },
    "done": true
  },
  "minecraft:recipes/building_blocks/polished_blackstone_brick_stairs": {
    "criteria": {
      "has_polished_blackstone_bricks": "2021-05-28 18:03:21 -0400"
    },
    "done": true
  },
  "minecraft:recipes/building_blocks/white_wool_from_string": {
    "criteria": {
      "has_string": "2021-05-28 17:53:02 -0400"
    },
    "done": true
  },
  "minecraft:recipes/tools/stone_hoe": {
    "criteria": {
      "has_cobblestone": "2021-05-28 17:53:02 -0400"
    },
    "done": true
  },
  "minecraft:recipes/building_blocks/sandstone_stairs": {
    "criteria": {
      "has_cut_sandstone": "2021-05-28 17:53:02 -0400"
    },
    "done": true
  },
  "minecraft:recipes/tools/wooden_hoe": {
    "criteria": {
      "has_stick": "2021-05-28 19:02:13 -0400"
    },
    "done": true
  },
  "minecraft:recipes/building_blocks/polished_andesite_stairs_from_polished_andesite_stonecutting": {
    "criteria": {
      "has_polished_andesite": "2021-05-28 18:39:53 -0400"
    },
    "done": true
  },
  "minecraft:recipes/building_blocks/cobblestone_slab": {
    "criteria": {
      "has_cobblestone": "2021-05-28 17:53:02 -0400"
    },
    "done": true
  },
  "minecraft:recipes/decorations/black_banner": {
    "criteria": {
      "has_black_wool": "2021-05-28 18:13:57 -0400"
    },
    "done": true
  },
  "minecraft:recipes/redstone/tripwire_hook": {
    "criteria": {
      "has_string": "2021-05-28 17:53:02 -0400"
    },
    "done": true
  },
  "minecraft:recipes/building_blocks/stone_stairs": {
    "criteria": {
      "has_stone": "2021-05-28 18:47:10 -0400"
    },
    "done": true
  },
  "minecraft:recipes/building_blocks/chiseled_quartz_block": {
    "criteria": {
      "has_quartz_pillar": "2021-05-28 17:53:02 -0400"
    },
    "done": true
  },
  "minecraft:recipes/building_blocks/cobblestone_stairs": {
    "criteria": {
      "has_cobblestone": "2021-05-28 17:53:02 -0400"
    },
    "done": true
  },
  "minecraft:recipes/building_blocks/oak_wood": {
    "criteria": {
      "has_log": "2021-05-28 18:18:16 -0400"
    },
    "done": true
  },
  "minecraft:recipes/building_blocks/polished_blackstone_brick_stairs_from_polished_blackstone_bricks_stonecutting": {
    "criteria": {
      "has_polished_blackstone_bricks": "2021-05-28 18:03:21 -0400"
    },
    "done": true
  },
  "minecraft:recipes/decorations/polished_blackstone_brick_wall_from_polished_blackstone_bricks_stonecutting": {
    "criteria": {
      "has_polished_blackstone_bricks": "2021-05-28 18:03:21 -0400"
    },
    "done": true
  },
  "minecraft:recipes/redstone/stone_button": {
    "criteria": {
      "has_stone": "2021-05-28 18:47:10 -0400"
    },
    "done": true
  },
  "minecraft:recipes/decorations/soul_campfire": {
    "criteria": {
      "has_stick": "2021-05-28 19:02:13 -0400"
    },
    "done": true
  },
  "minecraft:recipes/combat/crossbow": {
    "criteria": {
      "has_string": "2021-05-28 17:53:02 -0400"
    },
    "done": true
  },
  "minecraft:recipes/tools/stone_axe": {
    "criteria": {
      "has_cobblestone": "2021-05-28 17:53:02 -0400"
    },
    "done": true
  },
  "minecraft:recipes/building_blocks/bone_block": {
    "criteria": {
      "has_bonemeal": "2021-05-28 18:17:45 -0400"
    },
    "done": true
  },
  "minecraft:recipes/building_blocks/smooth_stone_slab_from_smooth_stone_stonecutting": {
    "criteria": {
      "has_smooth_stone": "2021-05-28 17:53:02 -0400"
    },
    "done": true
  },
  "DataVersion": 2586
}