{"stats":{"minecraft:dropped":{"minecraft:water_bucket":2,"minecraft:oak_log":1,"minecraft:glass_bottle":4,"minecraft:andesite_wall":2,"minecraft:leather":2,"minecraft:sheep_spawn_egg":1,"minecraft:grass_block":3,"minecraft:item_frame":3,"minecraft:music_disc_13":1,"minecraft:end_rod":1,"minecraft:spruce_leaves":1,"minecraft:cyan_terracotta":4,"minecraft:gray_concrete":1,"minecraft:grass":1,"minecraft:diorite":1,"minecraft:dispenser":1,"minecraft:black_stained_glass_pane":2,"minecraft:mutton":1,"minecraft:wooden_axe":9,"minecraft:white_concrete":7,"minecraft:smooth_quartz":1,"minecraft:map":2,"minecraft:potion":1,"minecraft:music_disc_strad":2,"minecraft:bone_meal":1,"minecraft:white_banner":21,"minecraft:music_disc_wait":1,"minecraft:smooth_stone":6,"minecraft:music_disc_stal":11,"minecraft:white_wool":1,"minecraft:music_disc_cat":1,"minecraft:spruce_sapling":1,"minecraft:redstone":1,"minecraft:dark_oak_door":2,"minecraft:bricks":5,"minecraft:blaze_rod":3,"minecraft:smooth_stone_slab":3,"minecraft:sticky_piston":1,"minecraft:fern":68,"minecraft:structure_block":2,"minecraft:ender_eye":5,"minecraft:name_tag":1,"minecraft:white_terracotta":1,"minecraft:oak_sign":1,"minecraft:flint_and_steel":1,"minecraft:filled_map":82,"minecraft:stone":1,"minecraft:flower_pot":64,"minecraft:dropper":1,"minecraft:acacia_slab":3,"minecraft:glowstone":5,"minecraft:blue_banner":1,"minecraft:music_disc_mall":1,"minecraft:birch_door":2,"minecraft:oak_boat":1,"minecraft:oak_sapling":18,"minecraft:redstone_torch":2,"minecraft:birch_sign":1,"minecraft:iron_bars":1,"minecraft:nether_quartz_ore":1,"minecraft:red_tulip":1,"minecraft:magma_block":1,"minecraft:oak_leaves":4},"minecraft:custom":{"minecraft:inspect_dropper":5,"minecraft:mob_kills":9,"minecraft:interact_with_crafting_table":12,"minecraft:open_shulker_box":12,"minecraft:leave_game":92,"minecraft:time_since_death":208695,"minecraft:climb_one_cm":329,"minecraft:sprint_one_cm":814916,"minecraft:walk_one_cm":5665057,"minecraft:drop":381,"minecraft:deaths":12,"minecraft:sneak_time":126573,"minecraft:walk_under_water_one_cm":456,"minecraft:boat_one_cm":9385,"minecraft:jump":9431,"minecraft:walk_on_water_one_cm":14507,"minecraft:play_record":49,"minecraft:interact_with_cartography_table":1,"minecraft:tune_noteblock":208,"minecraft:play_one_minute":4299439,"minecraft:interact_with_loom":24,"minecraft:sleep_in_bed":1,"minecraft:time_since_rest":208753,"minecraft:open_enderchest":19,"minecraft:damage_taken":1783,"minecraft:damage_dealt":1727,"minecraft:fly_one_cm":37489126,"minecraft:player_kills":2,"minecraft:open_chest":5,"minecraft:crouch_one_cm":48628,"minecraft:aviate_one_cm":1618898,"minecraft:fall_one_cm":5847,"minecraft:inspect_dispenser":46},"minecraft:used":{"minecraft:diorite_stairs":4,"minecraft:oak_fence":22,"minecraft:music_disc_far":2,"minecraft:nether_brick_fence":272,"minecraft:iron_bars":593,"minecraft:white_tulip":15,"minecraft:flint_and_steel":23,"minecraft:smooth_quartz_slab":223,"minecraft:armor_stand":11,"minecraft:dispenser":41,"minecraft:redstone":64,"minecraft:pufferfish_spawn_egg":1,"minecraft:poppy":2,"minecraft:oak_sign":18,"minecraft:white_concrete_powder":216,"minecraft:chest":4,"minecraft:white_terracotta":501,"minecraft:ender_chest":8,"minecraft:stone":141,"minecraft:zombie_spawn_egg":2,"minecraft:stripped_birch_wood":51,"minecraft:player_head":25,"minecraft:netherrack":47,"minecraft:oak_door":11,"minecraft:spruce_leaves":81,"minecraft:dirt":566,"minecraft:anvil":11,"minecraft:white_carpet":111,"minecraft:prismarine_bricks":63,"minecraft:hopper":1,"minecraft:nether_quartz_ore":2,"minecraft:brick_slab":57,"minecraft:prismarine_brick_stairs":218,"minecraft:nether_brick_slab":1,"minecraft:pink_terracotta":1,"minecraft:music_disc_13":1,"minecraft:music_disc_11":1,"minecraft:granite":184,"minecraft:spruce_fence":4,"minecraft:light_blue_stained_glass":2,"minecraft:nether_brick_stairs":131,"minecraft:polished_diorite":20,"minecraft:fern":1472,"minecraft:birch_door":325,"minecraft:andesite_wall":277,"minecraft:glass":745,"minecraft:red_shulker_box":1,"minecraft:cyan_terracotta":2332,"minecraft:acacia_slab":1411,"minecraft:stripped_dark_oak_wood":9,"minecraft:bricks":9094,"minecraft:red_tulip":28,"minecraft:light_gray_stained_glass":33,"minecraft:quartz_pillar":257,"minecraft:villager_spawn_egg":2,"minecraft:black_stained_glass_pane":1104,"minecraft:quartz_slab":269,"minecraft:red_wool":1,"minecraft:iron_block":30,"minecraft:lantern":18,"minecraft:grass_block":2944,"minecraft:blue_orchid":10,"minecraft:smooth_sandstone":3,"minecraft:brick_stairs":14,"minecraft:music_disc_ward":1,"minecraft:polished_andesite_stairs":105,"minecraft:music_disc_chirp":2,"minecraft:smooth_quartz":693,"minecraft:music_disc_wait":2,"minecraft:diorite_wall":21,"minecraft:music_disc_stal":33,"minecraft:item_frame":329,"minecraft:bedrock":74,"minecraft:repeater":6,"minecraft:glowstone":45,"minecraft:magma_block":1,"minecraft:redstone_lamp":14,"minecraft:black_stained_glass":430,"minecraft:oak_sapling":536,"minecraft:stone_pressure_plate":6,"minecraft:acacia_planks":184,"minecraft:large_fern":21,"minecraft:stripped_spruce_wood":4,"minecraft:dark_oak_stairs":1,"minecraft:water_bucket":82,"minecraft:nether_brick_wall":2,"minecraft:diorite":62,"minecraft:end_rod":1,"minecraft:damaged_anvil":1,"minecraft:pink_tulip":2,"minecraft:brick_wall":82,"minecraft:spruce_door":23,"minecraft:dropper":3,"minecraft:prismarine_brick_slab":301,"minecraft:birch_planks":112,"minecraft:gray_carpet":167,"minecraft:polished_andesite":277,"minecraft:oak_planks":7,"minecraft:cartography_table":1,"minecraft:blue_wool":12,"minecraft:andesite_slab":20,"minecraft:orange_tulip":21,"minecraft:black_shulker_box":9,"minecraft:cut_sandstone":1,"minecraft:spruce_sign":3,"minecraft:llama_spawn_egg":1,"minecraft:sheep_spawn_egg":1,"minecraft:stonecutter":3,"minecraft:smooth_quartz_stairs":290,"minecraft:oak_leaves":3273,"minecraft:white_wool":5,"minecraft:dark_oak_trapdoor":8,"minecraft:diamond_block":19,"minecraft:terracotta":56,"minecraft:music_disc_cat":1,"minecraft:light_blue_concrete":197,"minecraft:crafting_table":5,"minecraft:loom":3,"minecraft:birch_sign":41,"minecraft:light_gray_terracotta":3,"minecraft:yellow_concrete":33,"minecraft:note_block":6,"minecraft:gray_concrete":515,"minecraft:spruce_log":16,"minecraft:music_disc_strad":2,"minecraft:dark_oak_door":56,"minecraft:cyan_stained_glass":2029,"minecraft:birch_fence":13,"minecraft:redstone_torch":39,"minecraft:oak_log":402,"minecraft:sticky_piston":3,"minecraft:oxeye_daisy":2,"minecraft:piston":4,"minecraft:flower_pot":5,"minecraft:lever":8,"minecraft:ender_eye":12,"minecraft:acacia_stairs":47,"minecraft:black_concrete":84,"minecraft:cornflower":6,"minecraft:firework_rocket":42,"minecraft:daylight_detector":2,"minecraft:birch_fence_gate":11,"minecraft:acacia_sign":2,"minecraft:command_block":2,"minecraft:dark_oak_log":14,"minecraft:gray_stained_glass_pane":190,"minecraft:light_gray_concrete":32,"minecraft:music_disc_mall":1,"minecraft:stone_button":1,"minecraft:map":95,"minecraft:spruce_trapdoor":88,"minecraft:red_terracotta":41,"minecraft:iron_door":1,"minecraft:music_disc_blocks":3,"minecraft:spruce_sapling":13,"minecraft:gravel":117,"minecraft:polished_andesite_slab":481,"minecraft:yellow_wool":1,"minecraft:diamond_sword":23,"minecraft:zombie_pigman_spawn_egg":1,"minecraft:cobblestone":27,"minecraft:potion":9,"minecraft:orange_banner":1,"minecraft:cyan_stained_glass_pane":478,"minecraft:white_banner":13,"minecraft:dark_oak_fence":2,"minecraft:andesite":93,"minecraft:andesite_stairs":4,"minecraft:red_banner":1,"minecraft:smooth_stone_slab":1702,"minecraft:oak_boat":1,"minecraft:air":9424,"minecraft:white_concrete":7020,"minecraft:dandelion":15,"minecraft:cobweb":2,"minecraft:jukebox":45,"minecraft:bone_meal":2476,"minecraft:smooth_stone":6893,"minecraft:experience_bottle":3,"minecraft:gray_stained_glass":6},"minecraft:mined":{"minecraft:red_shulker_box":1},"minecraft:killed_by":{"minecraft:player":2,"minecraft:llama":1},"minecraft:crafted":{"minecraft:leather_leggings":3,"minecraft:leather_boots":3,"minecraft:filled_map":14,"minecraft:leather_helmet":2,"minecraft:leather_chestplate":3},"minecraft:picked_up":{"minecraft:wooden_axe":10,"minecraft:birch_door":34,"minecraft:music_disc_strad":2,"minecraft:azure_bluet":2,"minecraft:nether_brick_fence":1,"minecraft:redstone_lamp":1,"minecraft:leather_leggings":2,"minecraft:cornflower":1,"minecraft:music_disc_cat":2,"minecraft:elytra":1,"minecraft:smooth_stone_slab":1,"minecraft:flint_and_steel":1,"minecraft:item_frame":17,"minecraft:white_carpet":2,"minecraft:pufferfish":1,"minecraft:oak_sign":6,"minecraft:smooth_stone":5,"minecraft:redstone_torch":5,"minecraft:player_head":1,"minecraft:poppy":1,"minecraft:smooth_quartz":1,"minecraft:dark_oak_door":9,"minecraft:stick":221,"minecraft:stone":1,"minecraft:music_disc_blocks":2,"minecraft:stone_button":70,"minecraft:music_disc_11":1,"minecraft:redstone":10,"minecraft:andesite_wall":1,"minecraft:red_shulker_box":1,"minecraft:red_tulip":1,"minecraft:carved_pumpkin":2,"minecraft:cyan_terracotta":5,"minecraft:glowstone":2,"minecraft:blaze_rod":1,"minecraft:music_disc_wait":2,"minecraft:mutton":1,"minecraft:iron_bars":6,"minecraft:white_wool":1,"minecraft:cobblestone":13,"minecraft:oxeye_daisy":4,"minecraft:magma_block":1,"minecraft:leather_chestplate":2,"minecraft:water_bucket":1,"minecraft:leather":2,"minecraft:fern":3,"minecraft:music_disc_stal":53,"minecraft:filled_map":89,"minecraft:map":66,"minecraft:dirt":75,"minecraft:white_banner":7,"minecraft:leather_boots":2,"minecraft:glass":1,"minecraft:acacia_planks":1,"minecraft:apple":37,"minecraft:wheat_seeds":139,"minecraft:music_disc_far":3,"minecraft:music_disc_chirp":2,"minecraft:music_disc_13":2,"minecraft:dandelion":5,"minecraft:black_stained_glass_pane":1,"minecraft:grass_block":1,"minecraft:green_carpet":1,"minecraft:leather_helmet":2,"minecraft:firework_rocket":128,"minecraft:music_disc_mall":2,"minecraft:lever":4,"minecraft:grass":1,"minecraft:birch_sign":4,"minecraft:white_concrete":2,"minecraft:blue_banner":1,"minecraft:oak_sapling":321,"minecraft:acacia_slab":2,"minecraft:bricks":5,"minecraft:oak_leaves":4},"minecraft:killed":{"minecraft:pufferfish":1,"minecraft:ender_dragon":1,"minecraft:sheep":1,"minecraft:villager":6}},"DataVersion":1976}